sc_excel_column_calculator/__init__.py
sc_excel_column_calculator/main.py
sc_excel_column_calculator-0.0.6.dist-info/LICENSE
sc_excel_column_calculator-0.0.6.dist-info/METADATA
sc_excel_column_calculator-0.0.6.dist-info/WHEEL
sc_excel_column_calculator-0.0.6.dist-info/entry_points.txt
sc_excel_column_calculator-0.0.6.dist-info/top_level.txt
sc_excel_column_calculator-0.0.6.dist-info/RECORD
