Metadata-Version: 2.1
Name: sc-excel-column-calculator
Version: 0.0.6
Summary: python project
Home-page: https://github.com/Scott-Lau/sc-excel-column-calculator
Author: Scott Lau
Author-email: exceedego@126.com
License: MIT
Keywords: python
Platform: POSIX
Classifier: Programming Language :: Python :: 3
Classifier: Programming Language :: Python :: 3.6
Classifier: Programming Language :: Python :: 3.7
Classifier: Programming Language :: Python :: 3.8
Classifier: Programming Language :: Python :: 3.9
Classifier: License :: OSI Approved :: MIT License
Classifier: Operating System :: OS Independent
Classifier: Topic :: Software Development
Classifier: Topic :: Utilities
Requires-Python: >=3.6
License-File: LICENSE
Requires-Dist: sc-utilities (>=0.0.11)
